PivotGauss/__init__.py
PivotGauss/core.py
PivotGauss-1.0.2.dist-info/LICENSE.txt.
PivotGauss-1.0.2.dist-info/METADATA
PivotGauss-1.0.2.dist-info/WHEEL
PivotGauss-1.0.2.dist-info/top_level.txt
PivotGauss-1.0.2.dist-info/RECORD
